Workbook

Sheet Ejercicio 11
A3: 1 | B3: PV | C3: 25000
B4: Tasa de interés | C4: 0.1
B5: n años | C5: 5
A6: a | B6: PMT | C6: ? | D6: =PMT(C4,C5,C3) -> -6594.937
A9: b | B9: Periodo | C9: Saldo inicial | D9: Cuota | E9: Interés | F9: Amort. Capital | G9: Saldo final
B10: 1 | C10: =$C$3 -> 25000 | D10: =-$D$6 -> 6594.937 | E10: =C10*$C$4 -> 2500 | F10: =D10-E10 -> 4094.937 | G10: =C10-F10 -> 20905.063 | I10: =F10/D10 -> 0.62092132
B11: =B10+1 -> 2 | C11: =G10 -> 20905.063 | D11: =-$D$6 -> 6594.937 | E11: =C11*$C$4 -> 2090.5063 | F11: =D11-E11 -> 4504.4307 | G11: =C11-F11 -> 16400.632 | I11: =F11/D11 -> 0.68301346
B12: =B11+1 -> 3 | C12: =G11 -> 16400.632 | D12: =-$D$6 -> 6594.937 | E12: =C12*$C$4 -> 1640.0632 | F12: =D12-E12 -> 4954.8738 | G12: =C12-F12 -> 11445.758 | I12: =F12/D12 -> 0.7513148
B13: =B12+1 -> 4 | C13: =G12 -> 11445.758 | D13: =-$D$6 -> 6594.937 | E13: =C13*$C$4 -> 1144.5758 | F13: =D13-E13 -> 5450.3612 | G13: =C13-F13 -> 5995.3973 | I13: =F13/D13 -> 0.82644628
B14: =B13+1 -> 5 | C14: =G13 -> 5995.3973 | D14: =-$D$6 -> 6594.937 | E14: =C14*$C$4 -> 599.53973 | F14: =D14-E14 -> 5995.3973 | G14: =C14-F14 -> 0 | I14: =F14/D14 -> 0.90909091
A19: 2 | B19: Precio | C19: 160000
B20: Regalo | C20: 30000
B21: PV | C21: =C19-C20 -> 130000
B23: Opción A | F23: Opción B
B24: n años | C24: 3 | F24: TPA | G24: 0.05 | H24: Una opción era comparar tasas. B es mejor pues su tasa es menor a la de 6.76% que daba A
B25: m | C25: 12 | G25: =G24/C25 -> 0.0041666667
B26: n meses | C26: =C24*C25 -> 36 | F26: PMT | G26: =PMT(G25,C26,C21) -> -3896.2166 | H26: Otra opción es comparar pagos. B es mejor pues su pago es menor
B27: PMT | C27: -4000
B28: Tasa mensual | C28: ? | D28: =RATE(C26,C27,C21) -> 0.0056365248
B29: TPA | C29: ? | D29: =D28*C25 -> 0.067638298
A32: 3 | B32: Precio | C32: 125000
B33: Enganche | C33: 25000
B34: PV | C34: =C32-C33 -> 100000
B35: TPA | C35: 0.075
B36: Tasa mensual | C36: =C35/C37 -> 0.00625
B37: m | C37: 12
B38: n años | C38: 15
B39: n meses | C39: =C37*C38 -> 180
A40: a | B40: PMT | C40: ? | D40: =PMT(C36,C39,C34) -> -927.01236
A43: b | B43: TAE | C43: =EFFECT(C35,C37) -> 0.077632599 | F43: =C37 -> 12
B44: Cuota equivalente anual calculada con TAE | C44: =PMT(C43,C38,C34) -> -11514.621 | D44: Es igual a decir: | F44: =FV(C36,F43,D40) -> 11514.621 | G44: El valor futuro de 12 pagos de 927.01
B46: Periodo | C46: Saldo inicial | D46: Cuota | E46: Interés | F46: Amort. Capital | G46: Saldo final
B47: 1 | C47: =$C$34 -> 100000 | D47: =-$C$44 -> 11514.621 | E47: =C47*$C$43 -> 7763.2599 | F47: =D47-E47 -> 3751.3607 | G47: =C47-F47 -> 96248.639
B48: =B47+1 -> 2 | C48: =G47 -> 96248.639 | D48: =-$C$44 -> 11514.621 | E48: =C48*$C$43 -> 7472.032 | F48: =D48-E48 -> 4042.5886 | G48: =C48-F48 -> 92206.051
B49: =B48+1 -> 3 | C49: =G48 -> 92206.051 | D49: =-$C$44 -> 11514.621 | E49: =C49*$C$43 -> 7158.1953 | F49: =D49-E49 -> 4356.4252 | G49: =C49-F49 -> 87849.625
B50: =B49+1 -> 4 | C50: =G49 -> 87849.625 | D50: =-$C$44 -> 11514.621 | E50: =C50*$C$43 -> 6819.9947 | F50: =D50-E50 -> 4694.6259 | G50: =C50-F50 -> 83155
B51: =B50+1 -> 5 | C51: =G50 -> 83155 | D51: =-$C$44 -> 11514.621 | E51: =C51*$C$43 -> 6455.5387 | F51: =D51-E51 -> 5059.0819 | G51: =C51-F51 -> 78095.918 | H51: Saldo al finalizar el periodo 60 | K51: También puede calcularse así:
B52: =B51+1 -> 6 | C52: =G51 -> 78095.918 | D52: =-$C$44 -> 11514.621 | E52: =C52*$C$43 -> 6062.7891 | F52: =D52-E52 -> 5451.8315 | G52: =C52-F52 -> 72644.086 | J52: =B51*C37 -> 60 | K52: =FV(C36,J52,D40,C34) -> -78095.918 | L52: Signos deben ser inversos para obtener el saldo correcto
B53: =B52+1 -> 7 | C53: =G52 -> 72644.086 | D53: =-$C$44 -> 11514.621 | E53: =C53*$C$43 -> 5639.5492 | F53: =D53-E53 -> 5875.0714 | G53: =C53-F53 -> 66769.015
B54: =B53+1 -> 8 | C54: =G53 -> 66769.015 | D54: =-$C$44 -> 11514.621 | E54: =C54*$C$43 -> 5183.4521 | F54: =D54-E54 -> 6331.1684 | G54: =C54-F54 -> 60437.846
B55: =B54+1 -> 9 | C55: =G54 -> 60437.846 | D55: =-$C$44 -> 11514.621 | E55: =C55*$C$43 -> 4691.9471 | F55: =D55-E55 -> 6822.6735 | G55: =C55-F55 -> 53615.173
B56: =B55+1 -> 10 | C56: =G55 -> 53615.173 | D56: =-$C$44 -> 11514.621 | E56: =C56*$C$43 -> 4162.2852 | F56: =D56-E56 -> 7352.3354 | G56: =C56-F56 -> 46262.838
B57: =B56+1 -> 11 | C57: =G56 -> 46262.838 | D57: =-$C$44 -> 11514.621 | E57: =C57*$C$43 -> 3591.5043 | F57: =D57-E57 -> 7923.1163 | G57: =C57-F57 -> 38339.721
B58: =B57+1 -> 12 | C58: =G57 -> 38339.721 | D58: =-$C$44 -> 11514.621 | E58: =C58*$C$43 -> 2976.4122 | F58: =D58-E58 -> 8538.2084 | G58: =C58-F58 -> 29801.513
B59: =B58+1 -> 13 | C59: =G58 -> 29801.513 | D59: =-$C$44 -> 11514.621 | E59: =C59*$C$43 -> 2313.5689 | F59: =D59-E59 -> 9201.0517 | G59: =C59-F59 -> 20600.461
B60: =B59+1 -> 14 | C60: =G59 -> 20600.461 | D60: =-$C$44 -> 11514.621 | E60: =C60*$C$43 -> 1599.2673 | F60: =D60-E60 -> 9915.3533 | G60: =C60-F60 -> 10685.108
B61: =B60+1 -> 15 | C61: =G60 -> 10685.108 | D61: =-$C$44 -> 11514.621 | E61: =C61*$C$43 -> 829.51269 | F61: =D61-E61 -> 10685.108 | G61: =C61-F61 -> -6.184564e-11
A64: c | B64: Saldo inicial mes 61 | C64: =G51 -> 78095.918
B65: Tasa mensual | C65: =C36 -> 0.00625
B66: Interés mes 61 | C66: =C64*C65 -> 488.09949
A69: 4 | B69: PV | C69: 120000
B70: n | C70: 36
B71: PMT | C71: -4762
B72: tasa mensual | C72: =RATE(C70,C71,C69) -> 0.020712746
B73: m | C73: 12
B74: TPA | C74: =C72*C73 -> 0.24855295
A77: 5 | B77: n | C77: 10
B78: Tasa cupón | C78: 0.075
B79: Valor nominal | C79: 1000
B80: Cupón | C80: =C79*C78 -> 75
B81: YTM | C81: 0.07
A82: a | B82: PV | C82: =PV(C81,C77,C80,C79) -> -1035.1179
A85: b | B85: Inversión | C85: 50000000
B86: # de bonos a emitir | C86: =C85/C79 -> 50000
B87: Recaudación | C87: =-C86*C82 -> 51755895
A89: 6 | B89: PV | C89: 180000
B90: rate | C90: 0.08
B91: m | C91: 12
B92: r per | C92: =C90/C91 -> 0.0066666667
B93: n años | C93: 20
B94: n meses | C94: =C93*C91 -> 240
B95: PMT mensual | C95: ? | D95: =PMT(C92,C94,C89) -> -1505.5921
B96: TAE | C96: ? | D96: =EFFECT(C90,C91) -> 0.082999507
B97: PMT equivalente anual con TAE | C97: ? | D97: =PMT(D96,C93,C89) -> -18744.511
B100: Periodo | C100: Saldo inicial | D100: Cuota | E100: Interés | F100: Amort. Capital | G100: Saldo final
B101: 1 | C101: =$C$89 -> 180000 | D101: =-$D$97 -> 18744.511 | E101: =$D$96*C101 -> 14939.911 | F101: =D101-E101 -> 3804.5993 | G101: =C101-F101 -> 176195.4
B102: =B101+1 -> 2 | C102: =G101 -> 176195.4 | D102: =-$D$97 -> 18744.511 | E102: =$D$96*C102 -> 14624.131 | F102: =D102-E102 -> 4120.3792 | G102: =C102-F102 -> 172075.02
B103: =B102+1 -> 3 | C103: =G102 -> 172075.02 | D103: =-$D$97 -> 18744.511 | E103: =$D$96*C103 -> 14282.142 | F103: =D103-E103 -> 4462.3686 | G103: =C103-F103 -> 167612.65
B104: =B103+1 -> 4 | C104: =G103 -> 167612.65 | D104: =-$D$97 -> 18744.511 | E104: =$D$96*C104 -> 13911.768 | F104: =D104-E104 -> 4832.743 | G104: =C104-F104 -> 162779.91
B105: =B104+1 -> 5 | C105: =G104 -> 162779.91 | D105: =-$D$97 -> 18744.511 | E105: =$D$96*C105 -> 13510.652 | F105: =D105-E105 -> 5233.8583 | G105: =C105-F105 -> 157546.05
B106: =B105+1 -> 6 | C106: =G105 -> 157546.05 | D106: =-$D$97 -> 18744.511 | E106: =$D$96*C106 -> 13076.245 | F106: =D106-E106 -> 5668.266 | G106: =C106-F106 -> 151877.79
B107: =B106+1 -> 7 | C107: =G106 -> 151877.79 | D107: =-$D$97 -> 18744.511 | E107: =$D$96*C107 -> 12605.781 | F107: =D107-E107 -> 6138.7293 | G107: =C107-F107 -> 145739.06
B108: =B107+1 -> 8 | C108: =G107 -> 145739.06 | D108: =-$D$97 -> 18744.511 | E108: =$D$96*C108 -> 12096.27 | F108: =D108-E108 -> 6648.2408 | G108: =C108-F108 -> 139090.82
B109: =B108+1 -> 9 | C109: =G108 -> 139090.82 | D109: =-$D$97 -> 18744.511 | E109: =$D$96*C109 -> 11544.469 | F109: =D109-E109 -> 7200.0415 | G109: =C109-F109 -> 131890.77
B110: =B109+1 -> 10 | C110: =G109 -> 131890.77 | D110: =-$D$97 -> 18744.511 | E110: =$D$96*C110 -> 10946.869 | F110: =D110-E110 -> 7797.6414 | G110: =C110-F110 -> 124093.13
B111: =B110+1 -> 11 | C111: =G110 -> 124093.13 | D111: =-$D$97 -> 18744.511 | E111: =$D$96*C111 -> 10299.669 | F111: =D111-E111 -> 8444.8418 | G111: =C111-F111 -> 115648.29
B112: =B111+1 -> 12 | C112: =G111 -> 115648.29 | D112: =-$D$97 -> 18744.511 | E112: =$D$96*C112 -> 9598.7511 | F112: =D112-E112 -> 9145.7595 | G112: =C112-F112 -> 106502.53
B113: =B112+1 -> 13 | C113: =G112 -> 106502.53 | D113: =-$D$97 -> 18744.511 | E113: =$D$96*C113 -> 8839.6576 | F113: =D113-E113 -> 9904.853 | G113: =C113-F113 -> 96597.678
... B120: =B119+1 -> 20 | C120: =G119 -> 17307.959 | D120: =-$D$97 -> 18744.511 | E120: =$D$96*C120 -> 1436.552 | F120: =D120-E120 -> 17307.959 | G120: =C120-F120 -> 0
B123: Saldo año 10 | C123: =G110 -> 124093.13
B124: n años | C124: 10
B125: m | C125: 12
B126: n meses | C126: =C124*C125 -> 120
B127: rate | C127: 0.065
B128: r per | C128: =C127/C125 -> 0.0054166667
B129: Nuevo pmt | C129: ? | D129: =PMT(C128,C126,C123) -> -1409.0524
B132: n | C132: =C126 -> 120
B133: Ahorro en pmt | C133: =D129-D95 -> 96.539706
B134: rate | C134: =C128 -> 0.0054166667
B135: PV | C135: ? | D135: =PV(C134,C132,C133) -> -8502.1071 | E135: Valor presente de ahorros en cuota
...

Sheet Sheet2
B1: Tasa mensual | C1: ='Ejercicio 11'!C36 -> 0.00625
B2: Meses
C4: Saldo inicial | D4: Cuota | E4: Interes | F4: amort | G4: Saldo final
B5: 1 | C5: ='Ejercicio 11'!$C$34 -> 100000 | D5: =-'Ejercicio 11'!$D$40 -> 927.01236 | E5: =C5*$C$1 -> 625 | F5: =D5-E5 -> 302.01236 | G5: =C5-F5 -> 99697.988
B6: =B5+1 -> 2 | C6: =G5 -> 99697.988 | D6: =-'Ejercicio 11'!$D$40 -> 927.01236 | E6: =C6*$C$1 -> 623.11242 | F6: =D6-E6 -> 303.89994 | G6: =C6-F6 -> 99394.088
B7: =B6+1 -> 3 | C7: =G6 -> 99394.088 | D7: =-'Ejercicio 11'!$D$40 -> 927.01236 | E7: =C7*$C$1 -> 621.21305 | F7: =D7-E7 -> 305.79931 | G7: =C7-F7 -> 99088.288
B8: =B7+1 -> 4 | C8: =G7 -> 99088.288 | D8: =-'Ejercicio 11'!$D$40 -> 927.01236 | E8: =C8*$C$1 -> 619.3018 | F8: =D8-E8 -> 307.71056 | G8: =C8-F8 -> 98780.578
B9: =B8+1 -> 5 | C9: =G8 -> 98780.578 | D9: =-'Ejercicio 11'!$D$40 -> 927.01236 | E9: =C9*$C$1 -> 617.37861 | F9: =D9-E9 -> 309.63375 | G9: =C9-F9 -> 98470.944
B10: =B9+1 -> 6 | C10: =G9 -> 98470.944 | D10: =-'Ejercicio 11'!$D$40 -> 927.01236 | E10: =C10*$C$1 -> 615.4434 | F10: =D10-E10 -> 311.56896 | G10: =C10-F10 -> 98159.375
B11: =B10+1 -> 7 | C11: =G10 -> 98159.375 | D11: =-'Ejercicio 11'!$D$40 -> 927.01236 | E11: =C11*$C$1 -> 613.49609 | F11: =D11-E11 -> 313.51627 | G11: =C11-F11 -> 97845.859
B12: =B11+1 -> 8 | C12: =G11 -> 97845.859 | D12: =-'Ejercicio 11'!$D$40 -> 927.01236 | E12: =C12*$C$1 -> 611.53662 | F12: =D12-E12 -> 315.47574 | G12: =C12-F12 -> 97530.383
B13: =B12+1 -> 9 | C13: =G12 -> 97530.383 | D13: =-'Ejercicio 11'!$D$40 -> 927.01236 | E13: =C13*$C$1 -> 609.56489 | F13: =D13-E13 -> 317.44747 | G13: =C13-F13 -> 97212.936
B14: =B13+1 -> 10 | C14: =G13 -> 97212.936 | D14: =-'Ejercicio 11'!$D$40 -> 927.01236 | E14: =C14*$C$1 -> 607.58085 | F14: =D14-E14 -> 319.43151 | G14: =C14-F14 -> 96893.504
B15: =B14+1 -> 11 | C15: =G14 -> 96893.504 | D15: =-'Ejercicio 11'!$D$40 -> 927.01236 | E15: =C15*$C$1 -> 605.5844 | F15: =D15-E15 -> 321.42796 | G15: =C15-F15 -> 96572.076
B16: =B15+1 -> 12 | C16: =G15 -> 96572.076 | D16: =-'Ejercicio 11'!$D$40 -> 927.01236 | E16: =C16*$C$1 -> 603.57548 | F16: =D16-E16 -> 323.43688 | G16: =C16-F16 -> 96248.639
B17: =B16+1 -> 13 | C17: =G16 -> 96248.639 | D17: =-'Ejercicio 11'!$D$40 -> 927.01236 | E17: =C17*$C$1 -> 601.554 | F17: =D17-E17 -> 325.45836 | G17: =C17-F17 -> 95923.181
... B63: =B62+1 -> 59 | C63: =G62 -> 78965.582 | D63: =-'Ejercicio 11'!$D$40 -> 927.01236 | E63: =C63*$C$1 -> 493.53489 | F63: =D63-E63 -> 433.47747 | G63: =C63-F63 -> 78532.104
B64: =B63+1 -> 60 | C64: =G63 -> 78532.104 | D64: =-'Ejercicio 11'!$D$40 -> 927.01236 | E64: =C64*$C$1 -> 490.82565 | F64: =D64-E64 -> 436.18671 | G64: =C64-F64 -> 78095.918 | I64: =C1 -> 0.00625 | J64: =G64*I64 -> 488.09949
B65: =B64+1 -> 61 | C65: =G64 -> 78095.918 | D65: =-'Ejercicio 11'!$D$40 -> 927.01236 | E65: =C65*$C$1 -> 488.09949 | F65: =D65-E65 -> 438.91287 | G65: =C65-F65 -> 77657.005
B66: =B65+1 -> 62 | C66: =G65 -> 77657.005 | D66: =-'Ejercicio 11'!$D$40 -> 927.01236 | E66: =C66*$C$1 -> 485.35628 | F66: =D66-E66 -> 441.65608 | G66: =C66-F66 -> 77215.349
B67: =B66+1 -> 63 | C67: =G66 -> 77215.349 | D67: =-'Ejercicio 11'!$D$40 -> 927.01236 | E67: =C67*$C$1 -> 482.59593 | F67: =D67-E67 -> 444.41643 | G67: =C67-F67 -> 76770.932
B68: =B67+1 -> 64 | C68: =G67 -> 76770.932 | D68: =-'Ejercicio 11'!$D$40 -> 927.01236 | E68: =C68*$C$1 -> 479.81833 | F68: =D68-E68 -> 447.19403 | G68: =C68-F68 -> 76323.738
B69: =B68+1 -> 65 | C69: =G68 -> 76323.738 | D69: =-'Ejercicio 11'!$D$40 -> 927.01236 | E69: =C69*$C$1 -> 477.02336 | F69: =D69-E69 -> 449.989 | G69: =C69-F69 -> 75873.749
B70: =B69+1 -> 66 | C70: =G69 -> 75873.749 | D70: =-'Ejercicio 11'!$D$40 -> 927.01236 | E70: =C70*$C$1 -> 474.21093 | F70: =D70-E70 -> 452.80143 | G70: =C70-F70 -> 75420.948
B71: =B70+1 -> 67 | C71: =G70 -> 75420.948 | D71: =-'Ejercicio 11'!$D$40 -> 927.01236 | E71: =C71*$C$1 -> 471.38092 | F71: =D71-E71 -> 455.63144 | G71: =C71-F71 -> 74965.316
B72: =B71+1 -> 68 | C72: =G71 -> 74965.316 | D72: =-'Ejercicio 11'!$D$40 -> 927.01236 | E72: =C72*$C$1 -> 468.53323 | F72: =D72-E72 -> 458.47913 | G72: =C72-F72 -> 74506.837
B73: =B72+1 -> 69 | C73: =G72 -> 74506.837 | D73: =-'Ejercicio 11'!$D$40 -> 927.01236 | E73: =C73*$C$1 -> 465.66773 | F73: =D73-E73 -> 461.34463 | G73: =C73-F73 -> 74045.493
B74: =B73+1 -> 70 | C74: =G73 -> 74045.493 | D74: =-'Ejercicio 11'!$D$40 -> 927.01236 | E74: =C74*$C$1 -> 462.78433 | F74: =D74-E74 -> 464.22803 | G74: =C74-F74 -> 73581.265
B75: =B74+1 -> 71 | C75: =G74 -> 73581.265 | D75: =-'Ejercicio 11'!$D$40 -> 927.01236 | E75: =C75*$C$1 -> 459.8829 | F75: =D75-E75 -> 467.12946 | G75: =C75-F75 -> 73114.135
B76: =B75+1 -> 72 | C76: =G75 -> 73114.135 | D76: =-'Ejercicio 11'!$D$40 -> 927.01236 | E76: =C76*$C$1 -> 456.96335 | F76: =D76-E76 -> 470.04901 | G76: =C76-F76 -> 72644.086
... B184: =B183+1 -> 180 | C184: =G183 -> 921.25452 | D184: =-'Ejercicio 11'!$D$40 -> 927.01236 | E184: =C184*$C$1 -> 5.7578407 | F184: =D184-E184 -> 921.25452 | G184: =C184-F184 -> -1.4495072e-10
